privex/__init__.py
privex/curconv/__init__.py
privex/curconv/__main__.py
privex/curconv/app.py
privex/curconv/base.py
privex/curconv/ratesapi.py
privex/curconv/settings.py
privex/curconv/version.py
privex_curconv-0.5.0.data/scripts/conv
privex_curconv-0.5.0.dist-info/LICENSE
privex_curconv-0.5.0.dist-info/METADATA
privex_curconv-0.5.0.dist-info/WHEEL
privex_curconv-0.5.0.dist-info/top_level.txt
privex_curconv-0.5.0.dist-info/RECORD
