Metadata-Version: 2.1
Name: privex-curconv
Version: 0.5.0
Summary: Python Currency Converter CLI - A small CLI tool for quick currency conversions on the command line
Home-page: https://github.com/Privex/python-curconv
Author: Chris (Someguy123) @ Privex
Author-email: chris@privex.io
License: MIT
Platform: UNKNOWN
Classifier: Programming Language :: Python :: 3
Classifier: Programming Language :: Python :: 3.6
Classifier: Programming Language :: Python :: 3.7
Classifier: Programming Language :: Python :: 3.8
Classifier: Programming Language :: Python :: 3.9
Classifier: License :: OSI Approved :: MIT License
Classifier: Operating System :: POSIX :: Linux
Requires-Dist: privex-helpers (>=3)
Requires-Dist: privex-loghelper
Requires-Dist: httpx[http2]
Requires-Dist: python-dotenv
Requires-Dist: async-property
Requires-Dist: aiosqlite (>=0.12)
Requires-Dist: privex-db (>=0.9.2)
Provides-Extra: cache
Requires-Dist: privex-helpers[cache] ; extra == 'cache'
Provides-Extra: memcached
Requires-Dist: pylibmc ; extra == 'memcached'
Requires-Dist: aiomcache ; extra == 'memcached'
Provides-Extra: redis
Requires-Dist: aioredis (>=1.3) ; extra == 'redis'
Requires-Dist: hiredis ; extra == 'redis'
Requires-Dist: redis ; extra == 'redis'
